{
   "type": "minecraft:advancement_location",
   "pools": [
      {
         "bonus_rolls": 0,
         "entries": [
            {
               "type": "minecraft:item",
               "functions": [
                  {
                     "add": false,
                     "count": {
                        "type": "minecraft:uniform",
                        "max": 1,
                        "min": 1
                     },
                     "function": "minecraft:set_count"
                  }
               ],
               "name": "green_resurgence:material_cable_house",
               "weight": 20
            },
            {
               "type": "minecraft:item",
               "functions": [
                  {
                     "add": false,
                     "count": {
                        "type": "minecraft:uniform",
                        "max": 3,
                        "min": 1
                     },
                     "function": "minecraft:set_count"
                  }
               ],
               "name": "green_resurgence:material_metal_copperwire",
               "weight": 50
            },
            {
               "type": "minecraft:item",
               "functions": [
                  {
                     "add": false,
                     "count": {
                        "type": "minecraft:uniform",
                        "max": 1,
                        "min": 1
                     },
                     "function": "minecraft:set_count"
                  }
               ],
               "name": "green_resurgence:material_metal_lead1",
               "weight": 50
            },
            {
               "type": "minecraft:item",
               "functions": [
                  {
                     "add": false,
                     "count": {
                        "type": "minecraft:uniform",
                        "max": 1,
                        "min": 1
                     },
                     "function": "minecraft:set_count"
                  }
               ],
               "name": "green_resurgence:material_glass_window",
               "weight": 50
            },
            {
               "type": "minecraft:item",
               "functions": [
                  {
                     "add": false,
                     "count": {
                        "type": "minecraft:uniform",
                        "max": 1,
                        "min": 1
                     },
                     "function": "minecraft:set_count"
                  }
               ],
               "name": "green_resurgence:material_metal_copperplate",
               "weight": 50
            },
            {
               "type": "minecraft:item",
               "functions": [
                  {
                     "add": false,
                     "count": {
                        "type": "minecraft:uniform",
                        "max": 1,
                        "min": 1
                     },
                     "function": "minecraft:set_count"
                  }
               ],
               "name": "green_resurgence:material_alloy_brass",
               "weight": 50
            },
            {
               "type": "minecraft:item",
               "functions": [
                  {
                     "add": false,
                     "count": {
                        "type": "minecraft:uniform",
                        "max": 4,
                        "min": 1
                     },
                     "function": "minecraft:set_count"
                  }
               ],
               "name": "green_resurgence:material_adesive_screw",
               "weight": 50
            },
            {
               "type": "minecraft:item",
               "functions": [
                  {
                     "add": false,
                     "count": {
                        "type": "minecraft:uniform",
                        "max": 4,
                        "min": 1
                     },
                     "function": "minecraft:set_count"
                  }
               ],
               "name": "green_resurgence:material_adesive_nuts",
               "weight": 50
            },
            {
               "type": "minecraft:item",
               "functions": [
                  {
                     "add": false,
                     "count": {
                        "type": "minecraft:uniform",
                        "max": 2,
                        "min": 1
                     },
                     "function": "minecraft:set_count"
                  }
               ],
               "name": "green_resurgence:material_component_diode",
               "weight": 30
            },
            {
               "type": "minecraft:item",
               "functions": [
                  {
                     "add": false,
                     "count": {
                        "type": "minecraft:uniform",
                        "max": 1,
                        "min": 1
                     },
                     "function": "minecraft:set_count"
                  }
               ],
               "name": "green_resurgence:material_component_socket",
               "weight": 30
            },
            {
               "type": "minecraft:item",
               "functions": [
                  {
                     "add": false,
                     "count": {
                        "type": "minecraft:uniform",
                        "max": 1,
                        "min": 1
                     },
                     "function": "minecraft:set_count"
                  }
               ],
               "name": "green_resurgence:material_metal_ironbar",
               "weight": 50
            }
         ],
         "rolls": {
            "type": "minecraft:uniform",
            "max": 1,
            "min": 2
         }
      }
   ]
}