{
   "type": "minecraft:advancement_location",
   "pools": [
      {
         "bonus_rolls": 0,
         "entries": [
            {
               "type": "minecraft:item",
               "functions": [
                  {
                     "add": false,
                     "count": {
                        "type": "minecraft:uniform",
                        "max": 4,
                        "min": 1
                     },
                     "function": "minecraft:set_count"
                  }
               ],
               "name": "green_resurgence:material_metal_copperwire",
               "weight": 50
            },
            {
               "type": "minecraft:item",
               "functions": [
                  {
                     "add": false,
                     "count": {
                        "type": "minecraft:uniform",
                        "max": 2,
                        "min": 1
                     },
                     "function": "minecraft:set_count"
                  }
               ],
               "name": "green_resurgence:material_cables_tin",
               "weight": 40
            },
            {
               "type": "minecraft:item",
               "functions": [
                  {
                     "add": false,
                     "count": {
                        "type": "minecraft:uniform",
                        "max": 2,
                        "min": 1
                     },
                     "function": "minecraft:set_count"
                  }
               ],
               "name": "green_resurgence:material_cables_house",
               "weight": 20
            },
            {
               "type": "minecraft:item",
               "functions": [
                  {
                     "add": false,
                     "count": {
                        "type": "minecraft:uniform",
                        "max": 1,
                        "min": 1
                     },
                     "function": "minecraft:set_count"
                  }
               ],
               "name": "green_resurgence:material_cables_high",
               "weight": 10
            },
            {
               "type": "minecraft:item",
               "functions": [
                  {
                     "add": false,
                     "count": {
                        "type": "minecraft:uniform",
                        "max": 1,
                        "min": 1
                     },
                     "function": "minecraft:set_count"
                  }
               ],
               "name": "green_resurgence:material_metal_copperplate",
               "weight": 20
            },
            {
               "type": "minecraft:item",
               "functions": [
                  {
                     "add": false,
                     "count": {
                        "type": "minecraft:uniform",
                        "max": 4,
                        "min": 1
                     },
                     "function": "minecraft:set_count"
                  }
               ],
               "name": "green_resurgence:material_metal_scrap",
               "weight": 40
            }
         ],
         "rolls": {
            "type": "minecraft:uniform",
            "max": 1,
            "min": 1
         }
      }
   ]
}